firebase_auth_ui/__init__.py
firebase_auth_ui/draw_ui.py
firebase_auth_ui/authenticationUI/clicks.mp3
firebase_auth_ui/authenticationUI/diskaouApps.ico
firebase_auth_ui/authenticationUI/emailSent.mp3
firebase_auth_ui/authenticationUI/error.mp3
firebase_auth_ui/authenticationUI/internetConnection.png
firebase_auth_ui/authenticationUI/loginUI.png
firebase_auth_ui/authenticationUI/resetPassword.png
firebase_auth_ui/authenticationUI/signUpUI.png
firebase_auth_ui/authenticationUI/terms.png
firebase_auth_ui/authenticationUI/verifyEmail.png
firebase_auth_ui/fonts/Quicksand_Bold.otf
firebase_auth_ui/fonts/Quicksand_Bold_Oblique.otf
firebase_auth_ui/fonts/Quicksand_Book.otf
firebase_auth_ui/fonts/Quicksand_Book_Oblique.otf
firebase_auth_ui/fonts/Quicksand_Dash.otf
firebase_auth_ui/fonts/Quicksand_Light.otf
firebase_auth_ui/fonts/Quicksand_Light_Oblique.otf
firebase_auth_ui-0.0.3.dist-info/METADATA
firebase_auth_ui-0.0.3.dist-info/WHEEL
firebase_auth_ui-0.0.3.dist-info/licenses/LICENSE
firebase_auth_ui-0.0.3.dist-info/RECORD
