Metadata-Version: 2.1
Name: firebase_auth_ui
Version: 0.0.3
Summary: This package will help you to add authentication system and modern UI for your desktop based Python apps in a couple of seconds.
Project-URL: Homepage, https://github.com/PriomDeb/Firebase-Authentication-in-Python-Using-Tkinter
Project-URL: Bug Tracker, https://github.com/PriomDeb/Firebase-Authentication-in-Python-Using-Tkinter/issues
Author-email: Priom Deb <priom@priomdeb.com>
License: MIT License
Classifier: License :: OSI Approved :: MIT License
Classifier: Operating System :: OS Independent
Classifier: Programming Language :: Python :: 3
Requires-Python: >=3.7
Requires-Dist: pillow==9.2.0
Requires-Dist: pygame==2.1.2
Requires-Dist: pyglet==1.5.26
Requires-Dist: pyrebase4==4.5.0
